llama_index/embeddings/vllm/__init__.py
llama_index/embeddings/vllm/base.py
llama_index_embeddings_vllm-0.1.0.dist-info/METADATA
llama_index_embeddings_vllm-0.1.0.dist-info/WHEEL
llama_index_embeddings_vllm-0.1.0.dist-info/licenses/LICENSE
llama_index_embeddings_vllm-0.1.0.dist-info/RECORD
