Metadata-Version: 2.4
Name: llama-index-embeddings-vllm
Version: 0.1.0
Summary: llama-index embeddings vllm integration
Author-email: Yuri <yuri@yurinet.blog>
License-Expression: MIT
License-File: LICENSE
Requires-Python: <4.0,>=3.10
Requires-Dist: llama-index-core<0.14,>=0.13.0
Requires-Dist: vllm
